package/__init__.py
ch_rest_interface-0.0.1.dist-info/LICENSE
ch_rest_interface-0.0.1.dist-info/METADATA
ch_rest_interface-0.0.1.dist-info/WHEEL
ch_rest_interface-0.0.1.dist-info/top_level.txt
ch_rest_interface-0.0.1.dist-info/RECORD
