Metadata-Version: 2.1
Name: ch-rest-interface
Version: 0.0.1
Summary: ClickHouse REST interface
Home-page: https://github.com/pypa/sampleproject
Author: MzDehbashi
Author-email: mzdehbashi.jobmail@gmail.com
License: UNKNOWN
Platform: UNKNOWN
Classifier: Programming Language :: Python :: 3
Classifier: License :: OSI Approved :: MIT License
Classifier: Operating System :: OS Independent
Requires-Python: >=3.6
